demo/__init__.py
demo/highlight_elements.py
demo/make_elements_blink.py
tests/__init__.py
tests/test_webelement_highlighter.py
webelement_highlighter/__init__.py
webelement_highlighter-0.9.5.dist-info/LICENSE
webelement_highlighter-0.9.5.dist-info/METADATA
webelement_highlighter-0.9.5.dist-info/WHEEL
webelement_highlighter-0.9.5.dist-info/top_level.txt
webelement_highlighter-0.9.5.dist-info/RECORD
