Metadata-Version: 2.1
Name: webelement-highlighter
Version: 0.9.5
Summary: A simple package to highlight webelements
Home-page: https://github.com/rtorres90/webelement_highlighter
Author: Roberto Torres
Author-email: roberto.torres.dev@gmail.com
License: UNKNOWN
Project-URL: Bug Tracker, https://github.com/rtorres90/webelement_highlighter/issues
Platform: UNKNOWN
Classifier: Programming Language :: Python :: 3
Classifier: License :: OSI Approved :: MIT License
Classifier: Operating System :: OS Independent
Requires-Python: >=3.6
